{
  "css/chat_box.css": "css/chat_box-74e45097e5.css",
  "css/footer.css": "css/footer-e3c6dd4690.css",
  "css/header.css": "css/header-b29d8e3257.css",
  "css/home.css": "css/home-876c127e16.css",
  "css/layout.css": "css/layout-573d372b7b.css",
  "css/user_profile.css": "css/user_profile-f5f65c3380.css",
  "js/chat_engine.js": "js/chat_engine-766c2e2fee.js",
  "js/home_post_comments.js": "js/home_post_comments-f2d9695519.js",
  "js/home_posts.js": "js/home_posts-9ca1ca390e.js",
  "js/toggle_friends.js": "js/toggle_friends-d41d8cd98f.js",
  "js/toggle_likes.js": "js/toggle_likes-0e3d81481c.js"
}